ezloggers/__init__.py
ezloggers/ezloggers.py
ezloggers-1.1.2.dist-info/METADATA
ezloggers-1.1.2.dist-info/WHEEL
ezloggers-1.1.2.dist-info/top_level.txt
ezloggers-1.1.2.dist-info/RECORD
